public class org.jiakesimk.minipika.framework.beans.BeansManager {
  public org.jiakesimk.minipika.framework.beans.BeansManager();
    Code:
       0: aload_0
       1: invokespecial #1                  // Method java/lang/Object."<init>":()V
       4: return

  public static org.jiakesimk.minipika.components.db.NativeResult newNativeResult();
    Code:
       0: new           #4                  // class org/raniaia/minipika/framework/db/NativeResultMysql
       3: dup
       4: invokespecial #5                  // Method org/raniaia/minipika/framework/db/NativeResultMysql."<init>":()V
       7: areturn

  public static <T> T getBean(java.lang.String);
    Code:
       0: aload_0
       1: invokestatic  #17                 // Method factory:(Ljava/lang/String;)Ljava/lang/Object;
       4: astore_1
       5: aload_1
       6: areturn

  static {};
    Code:
       0: new           #59                 // class java/util/HashMap
       3: dup
       4: invokespecial #60                 // Method java/util/HashMap."<init>":()V
       7: putstatic     #18                 // Field beans:Ljava/util/Map;
      10: return
}
